voila/__init__.py
voila/__main__.py
voila/_version.py
voila/app.py
voila/configuration.py
voila/execute.py
voila/exporter.py
voila/handler.py
voila/notebook_renderer.py
voila/paths.py
voila/request_info_handler.py
voila/server_extension.py
voila/shutdown_kernel_handler.py
voila/static_file_handler.py
voila/treehandler.py
voila/utils.py
voila/voila_identity_provider.py
voila/voila_kernel_manager.py
voila/labextensions/jupyterlab-preview/package.json
voila/labextensions/jupyterlab-preview/schemas/@voila-dashboards/jupyterlab-preview/package.json.orig
voila/labextensions/jupyterlab-preview/schemas/@voila-dashboards/jupyterlab-preview/plugin.json
voila/labextensions/jupyterlab-preview/static/457.e999d1619bcc8f4fb8c7.js
voila/labextensions/jupyterlab-preview/static/541.d808f07c87cd740e80e7.js
voila/labextensions/jupyterlab-preview/static/remoteEntry.1f9ea21a72af73f668c2.js
voila/labextensions/jupyterlab-preview/static/style.js
voila/labextensions/jupyterlab-preview/static/third-party-licenses.json
voila/labextensions/widgets-manager7/package.json
voila/labextensions/widgets-manager7/static/122.c2a6c3e3d51be666e948.js
voila/labextensions/widgets-manager7/static/319.e94dd91f041d2e247d80.js
voila/labextensions/widgets-manager7/static/390.2bd817860474b4db8581.js
voila/labextensions/widgets-manager7/static/426.c5e5b9043007c2d49a71.js
voila/labextensions/widgets-manager7/static/496.5ad1f86424ee765927d6.js
voila/labextensions/widgets-manager7/static/532.66f7f70cb65040a15951.js
voila/labextensions/widgets-manager7/static/613.14503aaa01b08964833b.js
voila/labextensions/widgets-manager7/static/651.8b63c0297a39649bd115.js
voila/labextensions/widgets-manager7/static/651.8b63c0297a39649bd115.js.LICENSE.txt
voila/labextensions/widgets-manager7/static/714.9d564044485aa7f001c8.js
voila/labextensions/widgets-manager7/static/874.9f74b382ec69b566b879.js
voila/labextensions/widgets-manager7/static/941.b85b69a9ed4c002057b5.js
voila-0.5.10.dist-info/METADATA
voila-0.5.10.dist-info/WHEEL
voila-0.5.10.dist-info/entry_points.txt
voila-0.5.10.dist-info/licenses/LICENSE
voila-0.5.10.dist-info/RECORD
