Metadata-Version: 2.4
Name: voila
Version: 0.5.10
Summary: Voilà turns Jupyter notebooks into standalone web applications
Project-URL: Homepage, https://github.com/voila-dashboards/voila
Author: Voila Development Team
License: BSD License
License-File: LICENSE
Keywords: Jupyter,JupyterLab,Voila
Classifier: Framework :: Jupyter
Classifier: Framework :: Jupyter :: JupyterLab
Classifier: Framework :: Jupyter :: JupyterLab :: 3
Classifier: Framework :: Jupyter :: JupyterLab :: Extensions
Classifier: Framework :: Jupyter :: JupyterLab :: Extensions :: Prebuilt
Classifier: License :: OSI Approved :: BSD License
Classifier: Programming Language :: Python
Classifier: Programming Language :: Python :: 3
Classifier: Programming Language :: Python :: 3.7
Classifier: Programming Language :: Python :: 3.8
Classifier: Programming Language :: Python :: 3.9
Classifier: Programming Language :: Python :: 3.10
Classifier: Programming Language :: Python :: 3.11
Requires-Python: >=3.8
Requires-Dist: jupyter-client<9,>=7.4.4
Requires-Dist: jupyter-core>=4.11.0
Requires-Dist: jupyter-server<3,>=1.18
Requires-Dist: jupyterlab-server<3,>=2.3.0
Requires-Dist: nbclient>=0.4.0
Requires-Dist: nbconvert<8,>=6.4.5
Requires-Dist: traitlets<6,>=5.0.3
Requires-Dist: websockets>=9.0
Provides-Extra: dev
Requires-Dist: black; extra == 'dev'
Requires-Dist: hatch; extra == 'dev'
Requires-Dist: jupyter-releaser; extra == 'dev'
Requires-Dist: pre-commit; extra == 'dev'
Provides-Extra: docs
Requires-Dist: myst-parser; extra == 'docs'
Requires-Dist: pydata-sphinx-theme; extra == 'docs'
Requires-Dist: sphinx; extra == 'docs'
Requires-Dist: sphinx-autobuild; extra == 'docs'
Requires-Dist: sphinxcontrib-video; extra == 'docs'
Provides-Extra: test
Requires-Dist: ipykernel; extra == 'test'
Requires-Dist: ipywidgets; extra == 'test'
Requires-Dist: matplotlib; extra == 'test'
Requires-Dist: numpy; extra == 'test'
Requires-Dist: pandas; extra == 'test'
Requires-Dist: papermill; extra == 'test'
Requires-Dist: pytest; extra == 'test'
Requires-Dist: pytest-tornasync; extra == 'test'
Provides-Extra: test7
Requires-Dist: ipykernel; extra == 'test7'
Requires-Dist: ipywidgets==7.8.2; extra == 'test7'
Requires-Dist: matplotlib; extra == 'test7'
Requires-Dist: numpy; extra == 'test7'
Requires-Dist: pandas; extra == 'test7'
Requires-Dist: papermill; extra == 'test7'
Requires-Dist: pytest; extra == 'test7'
Requires-Dist: pytest-tornasync; extra == 'test7'
